{
  "antd_rollup": 832104,
  "antd_rollup_jsshaker": 658502,
  "antd_rollup_jsshaker.gz": 142255,
  "antd_rollup.gz": 167375,
  "glob_rollup_jsshaker": 205955,
  "glob_rollup_jsshaker.gz": 53752,
  "js-yaml_rollup_jsshaker": 63247,
  "js-yaml_rollup_jsshaker.gz": 14927,
  "lodash_rollup_jsshaker": 515935,
  "lodash_rollup_jsshaker.gz": 94209,
  "lodash-es_rollup_jsshaker": 57590,
  "lodash-es_rollup_jsshaker.gz": 14230,
  "material-ui_rollup_jsshaker": 330406,
  "material-ui_rollup_jsshaker.gz": 73519,
  "novnc_rollup_jsshaker": 427840,
  "novnc_rollup_jsshaker.gz": 110926,
  "rambda_rollup_heuristic": 2494,
  "rambda_rollup_heuristic.gz": 875,
  "rambda_rollup_jsshaker": 2222,
  "rambda_rollup_jsshaker.gz": 807,
  "rambdax_rollup_jsshaker": 5711,
  "rambdax_rollup_jsshaker.gz": 1997,
  "ramda_rollup_jsshaker": 21223,
  "ramda_rollup_jsshaker.gz": 5814,
  "react-icons_rollup_gcc_terser": 9505,
  "react-icons_rollup_gcc_terser.gz": 3709,
  "react-icons_rollup_jsshaker": 4387,
  "react-icons_rollup_jsshaker_gcc_terser": 3187,
  "react-icons_rollup_jsshaker_gcc_terser.gz": 1511,
  "react-icons_rollup_jsshaker_jsshaker": 4387,
  "react-icons_rollup_jsshaker_jsshaker_terser": 3260,
  "react-icons_rollup_jsshaker_jsshaker_terser.gz": 1538,
  "react-icons_rollup_jsshaker_jsshaker.gz": 1687,
  "react-icons_rollup_jsshaker_terser": 3260,
  "react-icons_rollup_jsshaker_terser.gz": 1537,
  "react-icons_rollup_jsshaker.gz": 1686,
  "react-icons_rollup_lacuna_gcc_terser": 5808,
  "react-icons_rollup_lacuna_gcc_terser.gz": 2480,
  "react-icons_rollup_lacuna_jsshaker_terser": 1747,
  "react-icons_rollup_lacuna_jsshaker_terser.gz": 918,
  "react-icons_rollup_lacuna_terser": 5849,
  "react-icons_rollup_lacuna_terser.gz": 2535,
  "react-icons_rollup_terser": 9510,
  "react-icons_rollup_terser.gz": 3735,
  "remeda_rollup_jsshaker": 4971,
  "remeda_rollup_jsshaker.gz": 1729,
  "rxjs_rollup_jsshaker": 17596,
  "rxjs_rollup_jsshaker.gz": 4152,
  "sentry_rollup_jsshaker": 271312,
  "sentry_rollup_jsshaker.gz": 76425,
  "test-simple_rollup_jsshaker": 47,
  "test-simple_rollup_jsshaker.gz": 61,
  "vuetify_rollup_jsshaker": 275842,
  "vuetify_rollup_jsshaker.gz": 70520
}